<object type="ch.idsia.evolution.MLP" id="0"><field name="firstConnectionLayer"><array type="[D" length="21" id="1"><array type="double" length="10" id="2">-7.0999000927453455 -2.9777586875647604 -1.273401823663178 -12.455867764504578 8.800715711375593 10.05820286459108 -0.7543524363318956 -2.2870178121135805 0.6882277871628252 1.5910684929070147</array><array type="double" length="10" id="3">-5.226919947027618 -4.187157975907189 1.6012254225094655 9.130398313829897 -6.011345695432735 -4.079215125423344 6.831037716776347 -2.165367981084371 0.17122918580403587 1.1685457652911422</array><array type="double" length="10" id="4">2.5635118863117676 11.012634756375242 -10.718712189727787 0.6271848403027624 7.86880780722143 4.299804397848092 -0.3252942585540724 -5.979468502915912 -4.112859636337514 2.2479943392574664</array><array type="double" length="10" id="5">-2.1899936835227014 -8.299313202051195 3.452620694668788 1.7481893381225744 -10.663342098732901 -8.282903334516208 0.41739979434097074 -2.20504273347937 -1.3527994825373348 7.071827090528302</array><array type="double" length="10" id="6">-3.008571465291732 4.880415381289579 1.9841989840840857 -2.0059452264924738 -7.085743257894872 4.123118779697759 -3.118896862985722 6.001852301019958 8.995511166975444 -5.047516507881279</array><array type="double" length="10" id="7">2.826967111665382 -4.518199704145905 3.349727312390968 4.026367251711457 1.2684028080180876 6.375238375367126 -2.441816464452365 -0.15879602324975922 10.619032851140961 -10.35925912489868</array><array type="double" length="10" id="8">-2.4255693004180685 -1.7940833762954902 2.435422612226363 -1.152672840932579 -7.321810508783701 11.98293603078545 5.032144106007536 -6.9198331960950865 -1.4747824268659093 5.912192883003747</array><array type="double" length="10" id="9">6.135770568399739 1.4866121600409936 2.9176923770656655 -6.995898963736348 -6.156452478483103 -5.1787347595228415 -3.1600994717782145 -9.989464218579455 -2.4686725348720717 -4.382856821111254</array><array type="double" length="10" id="10">0.3483700953427463 -0.8581109167024391 -1.1799742088396774 -8.726022646217727 -1.6026543519163965 -0.7382383093336252 -1.8396544235530703 5.452981742518724 -0.8578581603152027 -1.2818864815733013</array><array type="double" length="10" id="11">-1.011845142270815 -1.5226420339023918 -2.743809675288324 5.826795886464066 10.603685379280405 -5.872327865912801 8.727224274161946 -3.869275775754453 3.1135703195294484 -4.837732513625057</array><array type="double" length="10" id="12">-4.3622166267694436 -1.8024018658028584 -7.240069238463373 -4.756323984177609 5.50463465624894 1.192635893766705 -4.230267661711473 10.913607223671162 4.010119672880728 -7.180897394352374</array><array type="double" length="10" id="13">2.44492199515402 2.101508851994915 -1.4582884661491848 5.220361408739465 6.118854970214426 4.024794536869981 -0.8256173826253624 -4.832787718757235 4.080909940311041 -3.6480054761003706</array><array type="double" length="10" id="14">-0.12866891995574362 4.035368067757205 -6.918709502711345 -9.703925299168866 -3.3933323335657115 -7.899434305129294 -1.1758439167174068 5.637079229142966 0.3639323534655044 4.005611094944219</array><array type="double" length="10" id="15">-9.83500807485613 -2.2516709409612443 3.1153017139539325 5.0171604075101754 1.9038107348382929 -12.418758947460365 9.323699363824483 1.1725451245412664 10.403931962774612 -2.655015921874699</array><array type="double" length="10" id="16">-3.9181492772781503 -1.0632528834389199 0.9906399621521896 -3.991773311414329 -8.32561269364428 7.37779844106861 -3.932622095795304 -0.1947588808824362 1.6925888758112575 -0.2953116656753071</array><array type="double" length="10" id="17">3.717305902094106 -5.440246137149524 -4.005918788803632 -2.498519287804057 1.674619768105341 5.425656076273897 3.592345442123747 5.2956336173259455 -7.110429019724313 -7.71901359378151</array><array type="double" length="10" id="18">-0.6928698095797302 -3.3566877516002895 0.65802305295549 -2.4239455782955295 1.955157489934222 7.745254824984292 -3.1522374144209855 3.2145100232504404 1.0161032596741482 7.209794867442091</array><array type="double" length="10" id="19">1.843633173507405 5.905183617710422 -1.4735171069449122 -5.2924962611174635 6.184318087457974 4.6463036232139245 6.8595373438745995 -0.4320837091915597 8.761012667318239 -1.3091688690275043</array><array type="double" length="10" id="20">1.7355902327027974 0.6259360001459465 -0.00800467431851061 -2.545550842201746 -9.481365824509771 -2.7921216694280737 0.8378884010615849 -1.6329464760537995 -5.921657226429677 9.387585086017722</array><array type="double" length="10" id="21">6.255862596185858 3.6653417412479454 -3.233560165426568 2.704978421181815 1.7898229778010366 0.5122467777024605 -2.089555753885987 -2.910244942991138 -4.192709400358575 -6.178887591637412</array><array type="double" length="10" id="22">8.956279501042692 -3.689088096037165 2.97610167437525 3.1241870112968404 -4.769626483442174 -0.2978434663723049 -0.9836245228216205 -2.473216205592273 -6.06525543685444 2.0238288737522447</array></array></field><field name="secondConnectionLayer"><array type="[D" length="10" id="23"><array type="double" length="6" id="24">0.3298059992589882 0.3954157566463785 -5.058699791579288 8.510796985283868 4.550023120509831 -8.758003449162397</array><array type="double" length="6" id="25">3.437703103289503 0.25020277361287785 -4.458283132214112 4.0502680412462695 0.6811812563145836 -1.3578530416534413</array><array type="double" length="6" id="26">0.7433504532194749 6.07880985703633 -5.1538379869137305 3.510377829501568 2.0678240577787226 -1.525166541428259</array><array type="double" length="6" id="27">-6.121537852846508 -0.8329989876696361 -4.615001884490463 -5.1477422846484 1.4988200961339675 -8.180246597394444</array><array type="double" length="6" id="28">10.16160651452709 0.2138365578314555 -0.004371913632589125 14.937089003879022 -4.565203524581938 -0.25047664919531915</array><array type="double" length="6" id="29">-1.138516934682581 2.1108540188161147 -14.634568222225816 -4.445785815226008 -4.487504519860817 -2.8283765653356614</array><array type="double" length="6" id="30">8.140309503943799 5.879093433458103 9.232693586431017 -0.8428451298965043 3.1689244237582006 -9.1010148482165</array><array type="double" length="6" id="31">3.1981425248803217 -5.034294268414561 0.9483249914256721 -1.980425297584126 -1.746256164461784 -1.8314827061062542</array><array type="double" length="6" id="32">-1.8580386434054024 -5.927956424217717 5.266876807051507 -6.754707045657367 7.564806384119919 5.854160071647911</array><array type="double" length="6" id="33">3.9324622905988376 -6.378740184677107 -0.9605631560452444 2.7458876417730824 9.982249945597774 -2.6013061958635277</array></array></field><field name="hiddenNeurons"><array type="double" length="10" id="34">0.9999999667566749 -0.9987513016068946 0.9948132755023441 0.996140272024312 -0.9998560691747946 -0.2893378512855513 -0.7546306530317136 -0.9858829050405626 -0.9999892151596973 0.9656730001594507</array></field><field name="outputs"><array type="double" length="6" id="35">-1.0 0.9998732686450883 -1.0 0.8262008236839721 0.9999999999996506 -0.999999999999953</array></field><field name="inputs"><array type="double" length="21" id="36">0.0 0.0 0.0 0.0 0.0 0.0 0.0 0.0 0.0 0.0 0.0 0.0 0.0 0.0 0.0 0.0 0.0 0.0 0.0 0.0 1.0</array></field><field name="mutationMagnitude" type="double" value="0.1" /><field name="mean" type="double" value="0.0" /><field name="deviation" type="double" value="0.10000000149011612" /><field name="learningRate" type="double" value="0.01" /></object>