<object type="ch.idsia.evolution.MLP" id="0"><field name="firstConnectionLayer"><array type="[D" length="21" id="1"><array type="double" length="10" id="2">-0.9864917124478235 0.7059542976253085 -1.4856073397137202 -2.0595207074917745 4.112314676037961 -0.8879933736647405 2.440682134213829 -2.2336065703800903 2.305929909831111 2.131462259883293</array><array type="double" length="10" id="3">-1.6223850845402021 -1.2115994431318153 1.4880418569981695 0.4241316714430974 -2.5864761879544336 3.642816349303475 -0.45659947457044703 2.8857908334161557 3.0510397204786646 -1.2669342390322598</array><array type="double" length="10" id="4">0.2523651459268865 -1.9686987200339465 -1.6222392344718641 -1.4148417195670473 -0.7080302789009785 -1.225999123910855 0.8456835673331199 1.3649642433514564 -1.8281315694660292 0.031961002041802467</array><array type="double" length="10" id="5">-0.03602204045285939 3.63339845876495 -0.42865181062136615 2.9872077331173235 2.9721442644224094 1.753224630182455 -0.36274113467321883 -1.835342781898319 3.215116477937221 -4.410429861382191</array><array type="double" length="10" id="6">1.681969616228465 0.8068689187915101 1.4893391302028869 2.497834629985108 -2.1949495114476703 3.473871053527342 -0.5780530634116522 1.5856609205523848 -0.7303132489793457 -2.399646145648296</array><array type="double" length="10" id="7">2.980754132914646 0.7881800846144873 -1.6436931469447358 0.2070576919278286 4.184362660881491 0.20924485174912633 -3.107867620149537 2.91214395265488 -2.0373914783227294 2.397855098244268</array><array type="double" length="10" id="8">2.0877393633985646 -0.9990845568429397 4.567637571977205 3.0576565488266776 -3.344745164415443 0.2477427223810776 -1.1351632993063214 -1.4080143832383027 0.4519497775777889 0.539923234062113</array><array type="double" length="10" id="9">4.020563604446805 -1.4414839371878234 -2.0620872718800833 3.5436494104354264 0.13147126748659674 2.478592915562414 -0.9654424934423744 -2.507285685904439 0.5202490940497295 -0.002880456433275464</array><array type="double" length="10" id="10">3.548144800405385 -0.8368432976466305 3.078993200263184 -0.648109028509291 -1.4541507609521829 1.7570518935781085 0.31964257813447366 -1.7985395587601334 2.87450820393965 -0.14500695805193498</array><array type="double" length="10" id="11">-2.327454196238645 -2.6403215482676465 -3.5024985386881773 -2.3295428311720388 3.326579171406501 1.2562555589758337 1.9404783696517112 1.5433779449645273 -0.48454239835268004 -3.148242041414042</array><array type="double" length="10" id="12">1.3800691065083668 -2.8155472529357297 -0.5509464925784738 0.44392541376595157 3.5551678786797516 4.6666460983979405 -1.7733197969181806 -2.1626137636727454 1.9243083631176352 -3.186468816218804</array><array type="double" length="10" id="13">-2.6346492247914 4.350425777026756 3.212260790838111 0.38928949819415587 -2.4143637152238306 -2.5480105135442463 -2.99048355081013 1.7386785198408932 3.50710775727366 -0.4346736748579988</array><array type="double" length="10" id="14">3.5230268157495024 -0.4435201015620321 -2.504020854371101 2.989072488979918 2.182335151918995 1.228961751901977 -3.226000611763747 -2.6557705895821018 -0.16166168843514092 -0.6283782994046575</array><array type="double" length="10" id="15">-0.3859616511791177 -1.0278247440592887 -2.3238177494189514 0.24199647318789863 -2.5949405052657557 -3.4856469996546777 2.460355692195044 2.5572978320795885 -2.77913034766204 -0.8377110831991368</array><array type="double" length="10" id="16">3.345860964242478 -2.180194034525907 -0.7798597327292849 -2.6448052262106225 -2.0722720922609286 0.11611860085837288 1.9375294347717906 2.82224248207691 0.7006183431832977 -2.6231529034354146</array><array type="double" length="10" id="17">1.1611293462775814 -2.756647696696215 -2.1431270922572963 -0.34576944379761243 -1.7715287936062314 -3.7389619794010813 -0.8296313122881349 -1.8977641249258468 -1.3351006160880305 1.3386240917335892</array><array type="double" length="10" id="18">3.360905225463108 1.3725652833830468 -1.6944541397754787 1.0086988321085248 4.131170878929612 -1.707132184198334 -2.1338691713845206 -1.460938367014599 1.3537570453381698 0.7014998692430172</array><array type="double" length="10" id="19">0.4970241371563878 2.8780105192761942 1.2600540885122515 -2.4502560805184834 -2.3156710207956173 -2.1830262548081727 4.311280611989647 -2.90322057215024 -2.153358504056107 0.0141232792337605</array><array type="double" length="10" id="20">0.017151339525502955 0.09131451663112354 1.1230760666829358 0.13444062112230218 -0.4732076405582819 3.9624839350089416 1.1814355158452823 1.6933680356664422 -2.898152399632408 0.8714815087608858</array><array type="double" length="10" id="21">2.2084278126235337 1.6879967665529003 -1.381421975205928 -1.1725613249082998 3.4864154530336395 -1.642489936462639 -0.9435907742272317 3.1124156250672703 -4.141223533065302 -3.1007327626064294</array><array type="double" length="10" id="22">-1.6241884984116002 -3.006745292898213 2.371772604422442 3.880945554000008 -3.281804300978668 2.4525916314525675 -2.9034651192244705 -2.918947850059241 -2.4535965784805196 2.090880919478137</array></array></field><field name="secondConnectionLayer"><array type="[D" length="10" id="23"><array type="double" length="6" id="24">-1.4987304348716197 1.4016315847069951 -0.0782141628304447 4.404246594497866 3.2197631150108355 2.5886355182117966</array><array type="double" length="6" id="25">1.9395649505132835 2.0118537794903864 -0.6272126491437104 1.3508553492973365 -1.1889041373196396 -0.5496163355673698</array><array type="double" length="6" id="26">1.2806958199314393 -0.6754335059732006 -2.676088521621821 -0.21660344225127043 -0.09612736642093216 -1.789792998022654</array><array type="double" length="6" id="27">-3.316321312816454 -1.7076479159058755 -0.33451047427509295 -2.6987338284343987 -0.38490309454470145 -3.321046621799707</array><array type="double" length="6" id="28">1.641921357015667 -2.7432128385148804 -2.9638283785047137 -2.2597156790481163 -2.3515087056974906 2.1201792149848426</array><array type="double" length="6" id="29">1.4582944731701255 4.770913910408803 -1.6746348055112388 -0.8462731314972658 3.484260291664667 1.6406250524456056</array><array type="double" length="6" id="30">0.5240841725752213 -0.43796654345495967 2.481235652372707 -0.10981425070099632 0.6431245145766332 2.4204289611889274</array><array type="double" length="6" id="31">-2.193309228852697 2.933425743769609 2.325374119949403 2.138772473319881 0.567483150232476 -0.8168770362232646</array><array type="double" length="6" id="32">2.253408081848246 -1.583796599569254 -2.190497835849421 -2.9311268997532913 0.41727745689857687 -0.14624841677231032</array><array type="double" length="6" id="33">-0.4128005021271385 1.0218815435340671 -0.5711962855641571 -3.3756304336557803 -0.7819582240597469 1.0692983217636547</array></array></field><field name="hiddenNeurons"><array type="double" length="10" id="34">-0.9252294970196365 -0.9951208583046458 0.9827348982624768 0.9991490604685098 -0.9971824039235117 0.985292781665872 -0.994004734428042 -0.994187004412973 -0.9853220952090833 0.9699162704361445</array></field><field name="outputs"><array type="double" length="6" id="35">-0.9989160887395169 0.9506077683255929 -0.9994889878487788 -0.999999983684252 0.8109850160934737 -0.999999687264146</array></field><field name="inputs"><array type="double" length="21" id="36">0.0 0.0 0.0 0.0 0.0 0.0 0.0 0.0 0.0 0.0 0.0 0.0 0.0 0.0 0.0 0.0 0.0 0.0 0.0 0.0 1.0</array></field><field name="mutationMagnitude" type="double" value="0.1" /><field name="mean" type="double" value="0.0" /><field name="deviation" type="double" value="0.10000000149011612" /><field name="learningRate" type="double" value="0.01" /></object>