<object type="ch.idsia.evolution.MLP" id="0"><field name="firstConnectionLayer"><array type="[D" length="21" id="1"><array type="double" length="10" id="2">7.0251447840733094 4.037814748698633 2.9806077316361157 -2.9897469029104715 -0.44425490578357724 -4.613367399909573 -2.4085158017507924 2.505560852438271 -3.9993179022501235 -2.772217564197353</array><array type="double" length="10" id="3">-5.142281413964222 3.7101206971485645 3.112276577888693 -6.051647313161641 -2.964841530025009 -5.2520458832405765 -2.7509361297564383 8.652761916038823 0.41841527361353353 3.764119640216625</array><array type="double" length="10" id="4">-4.200894074329254 -1.9557813966647795 -1.2781342914224127 0.29154531306469533 -0.4228651472207952 3.4307357365666915 3.976586946000929 -4.113033025384624 0.5470199249749145 3.396561971444161</array><array type="double" length="10" id="5">-4.022959656707186 1.349533745111943 -0.039801240961468004 -3.044215517272074 4.099212789443889 5.661338357791649 2.4605766124013293 -1.5674992674216606 2.354937258164547 -2.921399001269163</array><array type="double" length="10" id="6">3.664530100112661 1.1469852087973704 3.106383951627502 5.081447220630211 -2.2349715752239794 -5.379862958225409 -0.21854433071513418 -4.558786057892603 5.73296963273576 -7.376103480889358</array><array type="double" length="10" id="7">7.254613720049411 -3.3951034533868016 -1.7315160122410782 5.530786989607548 -2.4852364142624896 -2.8422803925377655 2.354533683196741 2.1186499097436684 -7.780986156366223 5.526209213389377</array><array type="double" length="10" id="8">2.5933847440242555 3.8287979756587642 -1.0357827557429276 2.7991304128117096 -0.9274749764755987 4.775667171396594 -2.2755119686325527 2.5810557615484817 1.1693815236606944 -3.3199813261154896</array><array type="double" length="10" id="9">0.38766907936706985 0.8186078074257914 -3.5563134837451784 0.029796399890016936 7.911487180424662 -1.4008268311207541 -7.1051427521786525 2.1579771636258136 -6.064631094931446 2.8602906440195914</array><array type="double" length="10" id="10">-2.2849653645611827 -2.9591821225151884 3.8284279844916216 -0.8663710575698751 1.7827294493983294 -5.728491956907584 -0.07971001468861795 3.6232780724495637 -0.6575540455699265 0.3788764086297084</array><array type="double" length="10" id="11">-2.406457340049451 -5.77022804080878 2.8913979959360963 -6.364672366994821 1.5303424890970134 0.05724782854575439 3.7480949369664516 -2.8088295525133673 -1.8915078267300889 9.610605974249289</array><array type="double" length="10" id="12">-2.080981603936544 -3.8459423576095135 -2.7809873911831615 -0.14406287174917962 -3.1380594575165635 -2.767056581848137 -3.04257547082188 -4.033464361292089 5.063471801744757 -0.4965733182252509</array><array type="double" length="10" id="13">-3.663176206913557 -1.0855869233163327 -4.537126296850838 -3.075978085374319 -7.153147241286445 -1.0688425660718914 -4.304496429558634 -1.9481758594901333 -5.0597286413794 4.796157869035745</array><array type="double" length="10" id="14">-2.0694788923229104 -0.45651090741412476 -0.5233533478696013 1.4244784064855227 2.9164753459121897 -0.07465232129096813 3.529573931322946 -6.206008495552728 -1.0275660789368763 -2.5131203114679574</array><array type="double" length="10" id="15">1.0316668112888985 4.021364541504716 6.585731011851195 2.6673329769973977 -7.622960241508946 3.0670107907803166 -2.7051990484967403 -1.6158834755914429 6.795204455453492 -7.868895718432489</array><array type="double" length="10" id="16">-7.26239470339695 -3.839829580907004 1.7310655854067314 5.513469748485928 0.9176113174418917 -0.49263962599654665 0.7718731081099341 -4.817885051263934 -5.290727846013083 -3.175436019663097</array><array type="double" length="10" id="17">4.5534948915740445 1.2078495766337127 1.9629511090482263 7.850041905128641 2.5127073958812245 -9.610367733008458 -6.3808642307704355 -4.732140300823867 -3.691139676542428 -2.482819203208289</array><array type="double" length="10" id="18">-5.364985928356683 4.521789268420809 3.8657755715718127 5.675953388176987 -0.7080026875327731 -2.6138393782795153 0.26716886398632145 3.9242103483485735 -4.908307946939566 -2.556617495383995</array><array type="double" length="10" id="19">-0.10665657312281165 -3.5777668336547155 -5.494322461478234 3.6508608742910704 -7.269071307815885 -7.2122874165436555 -4.464726616149751 0.2986381504383939 -7.565433424634223 -7.219664779962541</array><array type="double" length="10" id="20">-3.1171498138206184 1.2227390643964098 -5.497148070491843 -5.674759019527315 -3.5163891688592948 -4.271344691124871 -4.296423604717985 1.2572750562283714 1.439786680590099 2.1404814911981767</array><array type="double" length="10" id="21">-3.807819574070798 4.864930302018738 2.0395306115605707 -4.042095591010549 0.47701095952157674 -3.447477071201178 -5.134232901574428 -4.9826737474982625 1.687347169193704 1.2457241478505574</array><array type="double" length="10" id="22">6.647333144459015 1.9055839015563385 -6.464898893695214 5.743765098178056 4.10743091008922 2.5284683078375485 -4.895047198554355 0.4399505259713847 -3.3392095388772827 6.08788532442063</array></array></field><field name="secondConnectionLayer"><array type="[D" length="10" id="23"><array type="double" length="6" id="24">-1.2121795421066808 3.8516090199280306 -3.0026204781435304 0.4317744376050645 3.6843652320651046 1.4436965028349584</array><array type="double" length="6" id="25">-3.9968595583842537 8.310933702894916 -3.3635051349665464 -2.4144151167444576 7.444435824423009 -1.5528770722481071</array><array type="double" length="6" id="26">0.0813011126018255 -5.857345227125297 3.0736345440977266 2.274754612375743 5.33279995050386 -1.531379642370463</array><array type="double" length="6" id="27">-1.655589426877644 -2.6583161765692465 3.334996929981476 -3.4107696144681308 -3.209137514355005 -3.880360497342398</array><array type="double" length="6" id="28">-0.2585544682227633 5.1200764061708295 -2.3189069052407247 2.7042382528344504 -4.69277851694127 4.776369833038072</array><array type="double" length="6" id="29">5.402617411949687 -0.5764653654078391 -6.975403482118921 -4.258922931459372 6.106233194076049 -4.953227765872348</array><array type="double" length="6" id="30">3.996521131654686 0.87183193187665 -0.7799942277856744 -1.8939322163828656 1.6947050611403807 -2.288010892981865</array><array type="double" length="6" id="31">-0.8090714396214215 6.8704364468474735 -3.355872406951274 -4.687963573386881 5.445675362885333 2.556270958437468</array><array type="double" length="6" id="32">-1.0556192831798348 4.557966604886764 -1.5494013582822506 2.2026289585653296 -7.186561490993737 1.913528106961675</array><array type="double" length="6" id="33">1.169862332069955 2.5542149567159864 4.877903516339298 4.147869552665224 -1.9366880247969889 2.5568925184156717</array></array></field><field name="hiddenNeurons"><array type="double" length="10" id="34">0.9999991867255691 0.9972424781952671 0.9985137660398495 0.9999999999678357 -0.9586709072465444 -0.9999999998241587 -0.9999999997608118 0.9999969993582565 -0.9996660645673289 0.999997360027731</array></field><field name="outputs"><array type="double" length="6" id="35">-0.999999999999499 0.9972666892765784 0.9999999999915768 -0.979977131604739 1.0 0.3347498307001785</array></field><field name="inputs"><array type="double" length="21" id="36">0.0 1.0 1.0 0.0 1.0 1.0 0.0 1.0 1.0 0.0 0.0 0.0 0.0 1.0 0.0 0.0 0.0 0.0 0.0 0.0 1.0</array></field><field name="mutationMagnitude" type="double" value="0.1" /><field name="mean" type="double" value="0.0" /><field name="deviation" type="double" value="0.10000000149011612" /><field name="learningRate" type="double" value="0.01" /></object>