<object type="ch.idsia.evolution.MLP" id="0"><field name="firstConnectionLayer"><array type="[D" length="53" id="1"><array type="double" length="10" id="2">-1.9997016529885983 -0.4721946654736202 -3.276637426640864 0.21690968558160206 -0.4579485921596545 -2.6785979062930334 0.2564111860731031 -1.2120122044413848 -0.5602363432168255 0.936360767886736</array><array type="double" length="10" id="3">1.924595089927836 2.0700310657598657 2.719111112474671 -3.4441136759448954 2.3703851976248798 -0.056236338123356155 -2.368170644618177 -1.1997219746996848 -3.9216944506397997 -2.6128467180998953</array><array type="double" length="10" id="4">-1.3383943859595422 -1.3323622578081349 0.6892170732193248 -1.1674357745002963 0.946476016162235 4.773484910352734 -3.0802194485746126 -0.4183080437179787 -3.6707255461230153 4.641335439888612</array><array type="double" length="10" id="5">2.138413664698025 -0.49575378925524094 0.6173710173633937 2.0447503583323776 -1.1956826394229687 -3.0691839189382484 2.4370728472131242 0.5358587078827854 -5.043768913837103 2.2197973120549213</array><array type="double" length="10" id="6">2.2151004251278152 0.6680897825274494 -2.79164846437891 -3.498846820973262 -2.1155894022741997 4.302465325188097 0.7056519647015564 -1.297363539287713 0.8524430323982604 -1.6670502618869136</array><array type="double" length="10" id="7">2.6789581689079713 -1.8718281627818691 3.9798261105092405 2.1746313490808302 -2.7711038511110155 -1.811234207091776 3.691901790832207 0.9257122972009448 0.1813850735640723 -0.46189948668775194</array><array type="double" length="10" id="8">-1.6192301333091121 1.4296274175788954 0.7507105526776721 0.4902798047220356 -0.0812934719808227 -1.9425507531988657 -0.23485866120101084 -4.6722188968520015 4.548943510841369 -0.5435036341927761</array><array type="double" length="10" id="9">-1.7999049595948313 2.0336768528772438 1.6336536479032764 2.800086268452765 0.35317937418203504 -2.7385732426754608 3.870592207756053 1.4692007104916507 0.9246602749377917 -1.808806933536638</array><array type="double" length="10" id="10">2.3879808142567818 -0.345953881649333 -3.0920221865844164 -3.4388023868877906 -2.195683588630448 3.9852456518618613 -1.6347265638722637 3.2491119936632655 -4.191508090430423 1.9903792052625915</array><array type="double" length="10" id="11">-0.9315243324413899 -1.1295009860253762 0.9138478140891069 2.1986617477960446 -1.8717338769457843 2.8163030840572927 -4.284431414725168 2.5924063351653546 3.2473634459188943 1.118318332186198</array><array type="double" length="10" id="12">-0.5970754266080331 -0.9067338718217863 3.011673766913919 -1.5886551963086126 2.2620627957660147 -5.489236209581749 -0.6987868765423988 0.29943438174077597 0.31288817792100776 3.562481748812113</array><array type="double" length="10" id="13">-3.1952524684516885 2.524043478297628 1.438649909482442 1.162664488122675 3.9130857399601617 -0.3914654804010904 -2.4370034073461437 2.04525291190133 -2.350180923295719 4.549884360022954</array><array type="double" length="10" id="14">-1.0798385587422783 -2.19330901220646 -1.695233304703236 -3.5937163585026215 -2.5600367661066703 -2.2763222409158685 4.096371796082044 2.3082918389709954 1.3009620795104548 0.5693359293931024</array><array type="double" length="10" id="15">4.902227898928064 1.6839723063049379 1.8358753067619058 -0.3439575821120111 -1.8297919908641553 2.5449937465088026 -1.5052458075656088 -5.694362973701947 2.60609745063714 4.6303236759665305</array><array type="double" length="10" id="16">-0.12058042166683292 3.8437911481519658 -1.2431540477848901 2.4993404413432847 2.065388130469656 3.2111792821923504 0.8639172164582978 -1.0988627066877936 -2.1995010669841446 4.1188985981657105</array><array type="double" length="10" id="17">-2.8324427842570272 -2.8733703681956815 -2.4725858859323786 1.7556680685182844 -0.25724781123735707 -1.1041560854063062 2.9029105320733137 2.4950760581840026 2.185935104214847 2.018610280047346</array><array type="double" length="10" id="18">-3.282057684789513 -0.3719444920509154 -1.3896040074179332 2.648312349860425 2.7198328128556093 -3.2482743971924526 0.2106665370678889 -3.730815758191994 -5.170418066676172 0.815421714830942</array><array type="double" length="10" id="19">2.9167445332193993 -5.51773657616744 1.6065396540636114 -3.2121525130644843 -1.5352902968164066 0.09995674514580166 -0.6051244520926724 -4.368206691416816 3.0140473127883105 3.4080174514702546</array><array type="double" length="10" id="20">0.8486882168493735 -4.9912528037604655 1.855745582670721 -1.9461029600983308 0.3963154365278687 2.979068301979365 1.7685633114738553 -0.5144480373319869 3.6672837405305527 -2.8922311054408625</array><array type="double" length="10" id="21">-2.1123346614690277 0.2974594564371733 4.2150261681047905 1.5756526672401274 3.0820714669929807 -3.664418189406382 -1.9907016079911903 -0.5125538286922013 2.6555267394605635 2.0634646413663846</array><array type="double" length="10" id="22">-0.8233501157752674 3.6324199737590774 4.4258178849269205 -2.737122208748498 5.211893211241623 -1.2979889517454153 -0.5209741994526595 0.017787380958940613 2.415048317680038 -1.025633724143753</array><array type="double" length="10" id="23">-4.66743105912704 2.539529209161078 1.5825891777371568 -0.6543664911089497 3.201302745578021 3.3528078001252424 1.6855614432185297 4.604320280585377 -3.0867404254395083 -4.467019697114473</array><array type="double" length="10" id="24">-0.012649542348176446 -1.3440377416748313 1.0539730363868594 -0.2250811032959099 2.6606000104031833 2.0820727027403505 -0.6344942182462938 -1.3253383901894176 -0.642250418971705 1.5257347930804288</array><array type="double" length="10" id="25">2.076579424963032 1.436153312746324 0.25174829404658905 -1.9277783691351837 -0.1821724383382779 -2.201590091941047 0.34023443318482616 2.412172668296482 0.9548486953408266 -1.2171990749953716</array><array type="double" length="10" id="26">0.4370920882924938 2.8793552846876493 -3.1217634636312614 -0.8526310898941785 -0.7786084329038971 1.9089825246846142 -1.7840359606116203 2.088527595814883 -2.1374915608536047 1.5406556675168352</array><array type="double" length="10" id="27">1.7767928577961318 -0.20445352142394402 0.23882775260977995 0.48445691028365223 -1.197607463833863 -2.6650642885977875 0.30384147302121933 1.5436552143890383 4.47628412678269 -1.6174918393804736</array><array type="double" length="10" id="28">-3.196465879233894 -0.09401275714634894 -2.948014116235633 -2.0539280641744257 0.2617417202746428 1.5870649515767177 -3.068040017971337 -0.8283309784377388 -0.8533370829733472 -1.3420250082321952</array><array type="double" length="10" id="29">-1.5263971944853212 0.04835420901289317 -2.4101151212821876 -1.493323804948838 -1.8468067321217123 -3.62671154692329 -1.8228239468069452 -2.9818339194777863 -0.2581327740966528 -3.0477627362814608</array><array type="double" length="10" id="30">-0.6066904309847645 1.9979559142290684 3.5024275847927937 -1.4023405688355597 -5.736183280731293 -3.949875527648678 -2.5379371672104742 -2.638029426749638 1.2068785188982016 2.377237958988475</array><array type="double" length="10" id="31">0.05729061350821252 -1.2679483581002002 -1.352134453114111 -1.8325699060472873 -4.845781514130925 1.1344904305954642 2.7814935520795325 -1.432850744301664 0.8628207978758851 0.5447270428715412</array><array type="double" length="10" id="32">-0.5775685723013037 -0.4078314983427793 1.989283461997268 -3.639291020496987 -3.0930663915802663 1.9710123691373085 -2.437559862669641 0.7825181116572417 5.403178952888739 0.9550009705367523</array><array type="double" length="10" id="33">2.894832804093909 1.7030043446603593 -1.7543878280224463 1.8626520467235177 -0.2218953066410978 0.35805755413448703 -0.6094946997862516 2.0819697513263375 0.041146805610287274 -0.007913005470073675</array><array type="double" length="10" id="34">-1.657146460082287 1.3600830394546688 -0.6131554690703633 -1.2210490321799816 -0.8980331556727139 0.6813300781962832 1.4700080480956865 -1.76707838026739 -4.183480833692981 -2.8091076107429673</array><array type="double" length="10" id="35">2.7026524168269237 -1.048458673882668 2.467303959875845 -3.942946167411659 1.8237763661262205 0.642891745828349 -2.5258466343798798 1.7331950003664227 1.0778838678534344 -3.458212912346734</array><array type="double" length="10" id="36">-2.4160933088417638 -3.6881808449219413 -5.113053056134012 -2.331885839400282 3.535917135159395 -4.575843947947721 -1.4741841442780628 -0.06104125995162435 -0.3930851220185283 1.0536919982619786</array><array type="double" length="10" id="37">-0.4832804580545804 4.401398261896027 -0.7387963623306246 0.24873567250382744 -2.3739079358145188 -2.1739466609814935 2.942132092481335 -1.2717323510941863 -4.047823341950301 0.035644565895387004</array><array type="double" length="10" id="38">1.6100324148794183 3.8412657889696007 -2.606504089980401 -1.0502397520401159 4.403867184893879 0.34735340901302614 0.14565984890483463 -0.5036770413177329 1.7425381863960299 4.4412254065119905</array><array type="double" length="10" id="39">-1.0682036280657834 3.9195840809015943 3.6160716999368328 -3.577616782387649 5.050332009773362 1.6969737713229032 0.6193412217733143 -4.545444879394371 4.597928311524129 2.0745331782375676</array><array type="double" length="10" id="40">-3.708461020295378 1.457827066778796 0.985876749045941 -2.4854559729453336 -0.2618983940514523 -0.1856354361738901 -2.698569886521238 -4.5823107324237276 1.1630425326409024 -1.5020014536035118</array><array type="double" length="10" id="41">1.4814203687456757 -2.7560005244670815 -0.8058122540003967 3.3021785835246367 0.18297085006752978 3.3609511198768622 1.0901230357284013 -3.663772478197916 0.9202050037513363 2.0023690646049475</array><array type="double" length="10" id="42">-0.053971058078328804 4.169171001114838 0.019014760369665762 -0.48940241412337926 -1.2668605172215694 -2.5355922499870016 -2.4776518875510165 0.19439722979345975 -1.2640154535011694 -1.6110966489481366</array><array type="double" length="10" id="43">-3.4628884854028823 2.548932701763752 -1.18671816196272 2.62684452087733 -3.2471110072546754 1.0447720804354206 0.2558288333847313 3.6256147005071324 3.614077425561214 2.4404639905803536</array><array type="double" length="10" id="44">-1.1930191291186758 -2.2782288516258697 -2.991879965872498 -0.7636529752452156 -2.924825878192789 1.895405405905212 2.8938173958174147 -3.195892937220734 -0.11116164289146258 -2.010872243438295</array><array type="double" length="10" id="45">-0.9432233031432139 -1.3814840309850411 1.6556857798379934 1.451886809387425 -2.4514168748413616 2.365110246835127 -2.9617245748463215 -1.2442251460923672 0.292678076458294 -0.5736859571487414</array><array type="double" length="10" id="46">-1.1674854670975614 -2.0302005958887803 1.4214178972791063 0.1597403386375511 -2.0903845094021727 -4.991451713943272 -4.80195045698116 3.6672721637553236 -2.561587941752815 -1.119689651204827</array><array type="double" length="10" id="47">3.038414386929161 3.6894790672802196 -4.7992833680772335 -0.7146273605816809 0.48491488326111637 1.2874334112519619 3.1557197621881943 -1.2821827571676792 1.1162574166966768 -3.311009095089871</array><array type="double" length="10" id="48">-2.347843744448999 -1.0762345948139793 -1.5764491535947864 -1.031006027582553 -1.4623156368223351 0.19721956013985986 3.3701197101461524 4.423391374267441 1.9649594455813442 -4.2466988153545175</array><array type="double" length="10" id="49">-0.9553966833987215 -0.9944101825022815 1.6610207373936952 -1.9166753242167653 -0.9509278366252794 4.457124602014159 -3.76297669174586 -1.4529948359820888 1.529210064749508 0.8710190693780815</array><array type="double" length="10" id="50">4.7924535125571195 4.307588574718605 -1.7819522475879717 -0.9978783639498772 1.4498737109458006 1.4476465002057242 -2.129802644789141 2.747416579653313 -0.7619188798755072 2.036771046118536</array><array type="double" length="10" id="51">3.3126676125512753 4.852693713234526 -2.7103185068459483 -2.3036371070378925 -0.7176017803773411 -0.5470448317230372 -1.3980210079779045 2.9249698308242125 6.030068218387695 -0.40996314584702875</array><array type="double" length="10" id="52">-0.5646012367486042 0.6067834664311383 -2.5720905460159944 -0.8832309372137441 -0.6698821591348054 -1.0008189402224863 0.33364362728813735 2.0765615107796522 -2.3585755722070556 2.5737333432098413</array><array type="double" length="10" id="53">1.395533722212852 -1.5517369634901932 -0.03171048491113182 4.018925588310495 -0.2212794075787975 3.6785131788510066 0.17751738766428582 1.5680946979286845 3.562486540750472 1.81572280524218</array><array type="double" length="10" id="54">3.214250675036473 0.8517653393210483 2.8405571535270915 1.1682834424530244 0.6820603667920337 -0.8531874530844825 -3.5913480244601166 1.6442674648332876 2.753362802792835 2.2334951390587348</array></array></field><field name="secondConnectionLayer"><array type="[D" length="10" id="55"><array type="double" length="6" id="56">2.5846914774547773 -1.247436665047009 -0.49747087708649645 1.535159669900174 -2.182978497164982 0.40384622468394826</array><array type="double" length="6" id="57">1.9520093820848152 4.785543456916438 1.0940298678408138 -0.07133657102122784 -2.443396421098032 -2.629839612965667</array><array type="double" length="6" id="58">-2.5787012587328157 1.6989831854024546 -0.9302591052041644 -2.1649724823112715 1.0991822186053306 3.276729566017903</array><array type="double" length="6" id="59">-1.7050943976231503 2.024385277778427 -0.35758979333941765 1.947862184309953 3.224224637126703 -2.941601437442567</array><array type="double" length="6" id="60">2.0258157258615226 1.435829294425971 -2.4949977926784195 2.924560319443573 0.7428157170101235 -2.541193565326975</array><array type="double" length="6" id="61">0.6890147061377012 -0.9083652798447228 0.16046415817712267 -0.7385253889479922 0.3516523166001644 -2.2767732685372897</array><array type="double" length="6" id="62">1.8825597234983065 -1.208017346063646 -4.97856523713037 -3.9436414508333875 1.570515610896845 -4.345425699346729</array><array type="double" length="6" id="63">-0.24140376088223692 2.7542223302150997 -0.2461772773657629 0.27980392712339563 3.942107849857786 3.4269642824629196</array><array type="double" length="6" id="64">-1.271591708443569 0.8732480645187111 -3.4082444554386404 -0.6761127821233115 2.1677059195853228 0.22818068677225112</array><array type="double" length="6" id="65">0.8963391967510672 2.355805243564197 -3.192842997265325 0.12726707197934006 1.5649198393613393 2.7034357702486154</array></array></field><field name="hiddenNeurons"><array type="double" length="10" id="66">-0.9993140629771365 0.9999999513448629 0.999999999961015 -0.9205560335470487 0.9999704762098883 0.948968545931849 -0.9999997706018364 0.15478562371133073 0.9999999994438856 0.999999999604428</array></field><field name="outputs"><array type="double" length="6" id="67">-0.8498309707397703 0.9999999996966913 -0.9951832411472276 0.09789455982740856 0.9376193950885008 0.999989035857167</array></field><field name="inputs"><array type="double" length="53" id="68">1.0 0.0 1.0 0.0 0.0 1.0 0.0 0.0 0.0 0.0 0.0 0.0 0.0 1.0 1.0 0.0 1.0 0.0 1.0 1.0 1.0 1.0 1.0 1.0 1.0 1.0 0.0 1.0 0.0 0.0 1.0 0.0 0.0 0.0 0.0 0.0 0.0 0.0 0.0 0.0 0.0 1.0 0.0 0.0 0.0 0.0 0.0 0.0 0.0 0.0 0.0 0.0 1.0</array></field><field name="mutationMagnitude" type="double" value="0.1" /><field name="mean" type="double" value="0.0" /><field name="deviation" type="double" value="0.10000000149011612" /><field name="learningRate" type="double" value="0.01" /></object>